Metadata-Version: 1.1
Name: hongchaseeing.print
Version: 0.1.1
Summary: 看这是什么,I donot know!
Home-page: https://github.com/
Author: haowen zhang
Author-email: 806670753@qq.com
License: UNKNOWN
Platform: UNKNOWN
Classifier: Programming Language :: Python :: 3
Classifier: License :: OSI Approved :: MIT License
Classifier: Operating System :: OS Independent
